peepsai/__init__.py
peepsai/agent.py
peepsai/llm.py
peepsai/peeps.py
peepsai/process.py
peepsai/task.py
peepsai/agents/__init__.py
peepsai/agents/parser.py
peepsai/agents/peeps_agent_executor.py
peepsai/agents/tools_handler.py
peepsai/agents/agent_builder/__init__.py
peepsai/agents/agent_builder/base_agent.py
peepsai/agents/agent_builder/base_agent_executor_mixin.py
peepsai/agents/agent_builder/utilities/__init__.py
peepsai/agents/agent_builder/utilities/base_output_converter.py
peepsai/agents/agent_builder/utilities/base_token_process.py
peepsai/agents/cache/__init__.py
peepsai/agents/cache/cache_handler.py
peepsai/cli/__init__.py
peepsai/cli/add_peeps_to_flow.py
peepsai/cli/cli.py
peepsai/cli/command.py
peepsai/cli/config.py
peepsai/cli/constants.py
peepsai/cli/create_flow.py
peepsai/cli/create_peeps.py
peepsai/cli/evaluate_peeps.py
peepsai/cli/git.py
peepsai/cli/install_peeps.py
peepsai/cli/kickoff_flow.py
peepsai/cli/peeps_chat.py
peepsai/cli/plot_flow.py
peepsai/cli/plus_api.py
peepsai/cli/provider.py
peepsai/cli/replay_from_task.py
peepsai/cli/reset_memories_command.py
peepsai/cli/run_peeps.py
peepsai/cli/train_peeps.py
peepsai/cli/update_peeps.py
peepsai/cli/utils.py
peepsai/cli/version.py
peepsai/cli/authentication/__init__.py
peepsai/cli/authentication/constants.py
peepsai/cli/authentication/main.py
peepsai/cli/authentication/token.py
peepsai/cli/authentication/utils.py
peepsai/cli/deploy/__init__.py
peepsai/cli/deploy/main.py
peepsai/cli/templates/__init__.py
peepsai/cli/templates/flow/.gitignore
peepsai/cli/templates/flow/README.md
peepsai/cli/templates/flow/__init__.py
peepsai/cli/templates/flow/main.py
peepsai/cli/templates/flow/pyproject.toml
peepsai/cli/templates/flow/peepz/poem_peeps/poem_peeps.py
peepsai/cli/templates/flow/peepz/poem_peeps/config/agents.yaml
peepsai/cli/templates/flow/peepz/poem_peeps/config/tasks.yaml
peepsai/cli/templates/flow/tools/__init__.py
peepsai/cli/templates/flow/tools/custom_tool.py
peepsai/cli/templates/peeps/.gitignore
peepsai-0.1.3.dist-info/METADATA
peepsai-0.1.3.dist-info/WHEEL
peepsai-0.1.3.dist-info/entry_points.txt
peepsai-0.1.3.dist-info/licenses/LICENSE
peepsai-0.1.3.dist-info/RECORD
